README
setup.py
djlanding/__init__.py
djlanding/models.py
djlanding/tests.py
djlanding/views.py
djlanding.egg-info/PKG-INFO
djlanding.egg-info/SOURCES.txt
djlanding.egg-info/dependency_links.txt
djlanding.egg-info/requires.txt
djlanding.egg-info/top_level.txt