Metadata-Version: 1.0
Name: djlanding
Version: 0.1.6
Summary: Basic landing page for Django projects.
Home-page: http://pypi.python.org/pypi/djlanding/
Author: NuageHQ
Author-email: djlanding@nuagehq.com
License: BSD
Keywords: landing django
Platform: UNKNOWN
